{
  "accessoires_animaux": [
    {
      "id": "collier-anti-aboiement",
      "nom": "Collier anti-aboiement",
      "slug": "collier-anti-aboiement",
      "prix": 29.99,
      "image_file": "collier.webp",
      "description": "Collier anti-aboiement rechargeable, pratique pour accompagner l'éducation du chien.",
      "details": [
        "Rechargeable USB",
        "Étanche IP67",
        "3 modes de correction"
      ],
      "url": "https://www.amazon.fr/dp/B0CJBXNM4F?th=1"
    }
  ],
  "maison": [
    {
      "id": "poubelle-papier",
      "nom": "Poubelle de papier",
      "slug": "poubelle-de-papier",
      "prix": 3.99,
      "image_file": "trash-v2.jpg",
      "description": "Accessoire maison compact et pratique pour le bureau ou la chambre.",
      "details": [
        "Compacte",
        "Légère",
        "Usage quotidien"
      ],
      "url": "https://www.amazon.fr/dp/B0DCPDV81F?th=1"
    }
  ],
  "auto": [
    {
      "id": "disque-a",
      "nom": "Disque A jeune conducteur",
      "slug": "disque-a-jeune-conducteur",
      "prix": 2.99,
      "image_file": "discA-v2.jpg",
      "description": "Disque A magnétique pour jeunes conducteurs.",
      "details": [
        "Magnétique",
        "Conforme",
        "Facile à poser"
      ],
      "url": "https://www.amazon.fr/dp/B0F66GN8FD?th=1"
    }
  ]
}
